odoo/addons/website_sale_product_reference_displayed/README.rst
odoo/addons/website_sale_product_reference_displayed/__init__.py
odoo/addons/website_sale_product_reference_displayed/__manifest__.py
odoo/addons/website_sale_product_reference_displayed/i18n/website_sale_product_reference_displayed.pot
odoo/addons/website_sale_product_reference_displayed/readme/CONTRIBUTORS.rst
odoo/addons/website_sale_product_reference_displayed/readme/DESCRIPTION.rst
odoo/addons/website_sale_product_reference_displayed/readme/USAGE.rst
odoo/addons/website_sale_product_reference_displayed/static/description/icon.png
odoo/addons/website_sale_product_reference_displayed/static/description/index.html
odoo/addons/website_sale_product_reference_displayed/views/website_sale_views.xml
odoo11_addon_website_sale_product_reference_displayed-11.0.1.0.0.99.dev4.dist-info/METADATA
odoo11_addon_website_sale_product_reference_displayed-11.0.1.0.0.99.dev4.dist-info/WHEEL
odoo11_addon_website_sale_product_reference_displayed-11.0.1.0.0.99.dev4.dist-info/top_level.txt
odoo11_addon_website_sale_product_reference_displayed-11.0.1.0.0.99.dev4.dist-info/RECORD
